itmlogic/__init__.py
itmlogic/_version.py
itmlogic/lrprop.py
itmlogic/diffraction_attenuation/__init__.py
itmlogic/diffraction_attenuation/adiff.py
itmlogic/diffraction_attenuation/aknfe.py
itmlogic/diffraction_attenuation/fht.py
itmlogic/los_attenuation/__init__.py
itmlogic/los_attenuation/alos.py
itmlogic/misc/__init__.py
itmlogic/misc/qerf.py
itmlogic/misc/qerfi.py
itmlogic/misc/qtile.py
itmlogic/preparatory_subroutines/__init__.py
itmlogic/preparatory_subroutines/dlthx.py
itmlogic/preparatory_subroutines/hzns.py
itmlogic/preparatory_subroutines/qlra.py
itmlogic/preparatory_subroutines/qlrpfl.py
itmlogic/preparatory_subroutines/qlrps.py
itmlogic/preparatory_subroutines/zlsq1.py
itmlogic/scatter_attenuation/__init__.py
itmlogic/scatter_attenuation/ahd.py
itmlogic/scatter_attenuation/ascat.py
itmlogic/scatter_attenuation/h0f.py
itmlogic/statistics/__init__.py
itmlogic/statistics/avar.py
itmlogic/statistics/curv.py
itmlogic-1.2.dist-info/METADATA
itmlogic-1.2.dist-info/WHEEL
itmlogic-1.2.dist-info/licenses/LICENSE
itmlogic-1.2.dist-info/RECORD
