Metadata-Version: 2.4
Name: itmlogic
Version: 1.2
Summary: Longley-Rice irregular terrain propagation model
Project-URL: Homepage, https://github.com/edwardoughton/itmlogic
Author-email: Ed Oughton <edward.oughton@gmail.com>
License-Expression: MIT
License-File: LICENSE
Keywords: Longley-Rice,irregular terrain model,propagation model
Classifier: Development Status :: 1 - Planning
Classifier: Intended Audience :: Developers
Classifier: License :: OSI Approved :: MIT License
Classifier: Programming Language :: Python
Classifier: Programming Language :: Python :: 3
Classifier: Topic :: Scientific/Engineering :: GIS
Classifier: Topic :: Utilities
Requires-Dist: numpy
